heartkit/__init__.py
heartkit/__main__.py
heartkit/cli.py
heartkit/defines.py
heartkit/assets/__init__.py
heartkit/assets/data/__init__.py
heartkit/assets/data/nstdb.h5
heartkit/backends/__init__.py
heartkit/backends/backend.py
heartkit/backends/evb.py
heartkit/backends/pc.py
heartkit/backends/utils.py
heartkit/backends/GenericDataOperations_EvbToPc/__init__.py
heartkit/backends/GenericDataOperations_EvbToPc/client.py
heartkit/backends/GenericDataOperations_EvbToPc/common.py
heartkit/backends/GenericDataOperations_EvbToPc/interface.py
heartkit/backends/GenericDataOperations_EvbToPc/server.py
heartkit/backends/GenericDataOperations_PcToEvb/__init__.py
heartkit/backends/GenericDataOperations_PcToEvb/client.py
heartkit/backends/GenericDataOperations_PcToEvb/common.py
heartkit/backends/GenericDataOperations_PcToEvb/interface.py
heartkit/backends/GenericDataOperations_PcToEvb/server.py
heartkit/backends/erpc/__init__.py
heartkit/backends/erpc/arbitrator.py
heartkit/backends/erpc/basic_codec.py
heartkit/backends/erpc/client.py
heartkit/backends/erpc/codec.py
heartkit/backends/erpc/crc16.py
heartkit/backends/erpc/erpc_version.py
heartkit/backends/erpc/server.py
heartkit/backends/erpc/simple_server.py
heartkit/backends/erpc/transport.py
heartkit/datasets/__init__.py
heartkit/datasets/augmentation.py
heartkit/datasets/bidmc.py
heartkit/datasets/dataloader.py
heartkit/datasets/dataset.py
heartkit/datasets/defines.py
heartkit/datasets/ecg_synthetic.py
heartkit/datasets/factory.py
heartkit/datasets/icentia11k.py
heartkit/datasets/icentia_mini.py
heartkit/datasets/lsad.py
heartkit/datasets/ludb.py
heartkit/datasets/nstdb.py
heartkit/datasets/ppg_synthetic.py
heartkit/datasets/ptbxl.py
heartkit/datasets/qtdb.py
heartkit/models/__init__.py
heartkit/tasks/__init__.py
heartkit/tasks/task.py
heartkit/tasks/utils.py
heartkit/tasks/beat/__init__.py
heartkit/tasks/beat/datasets.py
heartkit/tasks/beat/defines.py
heartkit/tasks/beat/demo.py
heartkit/tasks/beat/evaluate.py
heartkit-1.8.0.dist-info/licenses/LICENSE
heartkit-1.8.0.dist-info/METADATA
heartkit-1.8.0.dist-info/WHEEL
heartkit-1.8.0.dist-info/entry_points.txt
heartkit-1.8.0.dist-info/top_level.txt
heartkit-1.8.0.dist-info/RECORD
